lppn/__init__.py
lppn/_version.py
lppn/cli.py
lppn/lppn.py
lppn-1.0.4.dist-info/LICENSE
lppn-1.0.4.dist-info/METADATA
lppn-1.0.4.dist-info/WHEEL
lppn-1.0.4.dist-info/entry_points.txt
lppn-1.0.4.dist-info/top_level.txt
lppn-1.0.4.dist-info/RECORD
