Metadata-Version: 2.1
Name: lppn
Version: 1.0.4
Summary: Print the latest Python patch number of a given major and minor version
Author-email: President Not Sure <144360653+president-not-sure@users.noreply.github.com>
License: MIT License
Project-URL: Homepage, https://github.com/president-not-sure/lppn
Project-URL: Repository, https://github.com/president-not-sure/lppn.git
Project-URL: Issues, https://github.com/president-not-sure/lppn/issues
Keywords: get,latest,python,patch,version
Classifier: Development Status :: 4 - Beta
Classifier: Programming Language :: Python :: 3
Classifier: License :: OSI Approved :: MIT License
Classifier: Operating System :: OS Independent
Classifier: Intended Audience :: Developers
Requires-Python: >=3.8
License-File: LICENSE
Requires-Dist: requests >=2.32.3
Provides-Extra: dev
